<oofem version="1">
  <Output>nlisomoisture01.out</Output>
  <Description>test of nonlinear isotropic material for moisture transport</Description>
  <Analysis type="TransientTransport" nsteps="5" alpha="0.5" lumped="" forcescale="0.0" forcescaledofs="14" rtolf="1e-05" prescribedtimes="0.01 0.1 0.2 0.3 0.4"/>
  <!-- nmodules 1 -->
  <!-- vtkxml tstep_all domain_all primvars 1 3 -->
  <Domain domain="mass1transfer">
    <OutputManager tsteps_out="5" dofman_output="1,7,13,19,25,31,37" element_output="1"/>
    <Nodes>
      <Node coords="0.0 0.0 0.0"/>
      <Node coords="0.001 0.0 0.0"/>
      <Node coords="0.002 0.0 0.0"/>
      <Node coords="0.0 0.001 0.0"/>
      <Node id="5" coords="0.001 0.001 0.0"/>
      <Node coords="0.002 0.001 0.0"/>
      <Node coords="0.0 0.002 0.0"/>
      <Node coords="0.001 0.002 0.0"/>
      <Node coords="0.002 0.002 0.0"/>
      <Node id="10" coords="0.0 0.003 0.0"/>
      <Node coords="0.001 0.003 0.0"/>
      <Node coords="0.002 0.003 0.0"/>
      <Node coords="0.0 0.004 0.0"/>
      <Node coords="0.001 0.004 0.0"/>
      <Node id="15" coords="0.002 0.004 0.0"/>
      <Node coords="0.0 0.005 0.0"/>
      <Node coords="0.001 0.005 0.0"/>
      <Node coords="0.002 0.005 0.0"/>
      <Node coords="0.0 0.006 0.0"/>
      <Node id="20" coords="0.001 0.006 0.0"/>
      <Node coords="0.002 0.006 0.0"/>
      <Node coords="0.0 0.007 0.0"/>
      <Node coords="0.001 0.007 0.0"/>
      <Node coords="0.002 0.007 0.0"/>
      <Node id="25" coords="0.0 0.008 0.0"/>
      <Node coords="0.001 0.008 0.0"/>
      <Node coords="0.002 0.008 0.0"/>
      <Node coords="0.0 0.009 0.0"/>
      <Node coords="0.001 0.009 0.0"/>
      <Node id="30" coords="0.002 0.009 0.0"/>
      <Node coords="0.0 0.01 0.0"/>
      <Node coords="0.001 0.01 0.0"/>
      <Node coords="0.002 0.01 0.0"/>
      <Node coords="0.0 0.011 0.0"/>
      <Node id="35" coords="0.001 0.011 0.0"/>
      <Node coords="0.002 0.011 0.0"/>
      <Node coords="0.0 0.012 0.0"/>
      <Node coords="0.001 0.012 0.0"/>
      <Node coords="0.002 0.012 0.0"/>
      <Node id="40" coords="0.0 0.013 0.0"/>
      <Node coords="0.001 0.013 0.0"/>
      <Node coords="0.002 0.013 0.0"/>
    </Nodes>
    <Elements>
      <quad1mt nodes="4 5 2 1" crosssect="1"/>
      <quad1mt nodes="5 6 3 2" crosssect="1"/>
      <quad1mt nodes="10 11 8 7" crosssect="2"/>
      <quad1mt nodes="11 12 9 8" crosssect="2"/>
      <quad1mt id="5" nodes="16 17 14 13" crosssect="3"/>
      <quad1mt nodes="17 18 15 14" crosssect="3"/>
      <quad1mt nodes="22 23 20 19" crosssect="4"/>
      <quad1mt nodes="23 24 21 20" crosssect="4"/>
      <quad1mt nodes="28 29 26 25" crosssect="5"/>
      <quad1mt id="10" nodes="29 30 27 26" crosssect="5"/>
      <quad1mt nodes="34 35 32 31" crosssect="6"/>
      <quad1mt nodes="35 36 33 32" crosssect="6"/>
      <quad1mt nodes="40 41 38 37" crosssect="7"/>
      <quad1mt nodes="41 42 39 38" crosssect="7"/>
    </Elements>
    <CrossSections>
      <SimpleTransportCS thickness="1.0" mat="1"/>
      <SimpleTransportCS thickness="1.0" mat="2"/>
      <SimpleTransportCS thickness="1.0" mat="3"/>
      <SimpleTransportCS thickness="1.0" mat="4"/>
      <SimpleTransportCS id="5" thickness="1.0" mat="5"/>
      <SimpleTransportCS thickness="1.0" mat="6"/>
      <SimpleTransportCS thickness="1.0" mat="7"/>
    </CrossSections>
    <Materials>
      <!-- constant capacity + BN permeability -->
      <nlisomoisturemat d="2400.0" isothermtype="0" permeabilitytype="1" capa="100.0" c1="0.0015" alpha0="0.1" hc="0.75" n="10.0"/>
      <!-- piecewise linear capacity + BN permeability -->
      <nlisomoisturemat d="2400.0" isothermtype="1" iso_h="0.0 0.2 0.6 0.8 0.9 1.0" iso_w_h_="0.0 20.0 40.0 60.0 80.0 130.0" permeabilitytype="1" c1="0.0015" alpha0="0.1" hc="0.75" n="10.0"/>
      <!-- Ricken capacity + BN permeability -->
      <nlisomoisturemat d="2400.0" isothermtype="2" dd="0.022" permeabilitytype="1" c1="0.0015" alpha0="0.1" hc="0.75" n="10.0"/>
      <!-- Kuenzel capacity + BN permeability -->
      <nlisomoisturemat d="2400.0" isothermtype="3" wf="130.0" b="1.3" permeabilitytype="1" c1="0.0015" alpha0="0.1" hc="0.75" n="10.0"/>
      <!-- Hansen capacity + BN permeability -->
      <nlisomoisturemat id="5" d="2400.0" isothermtype="4" rhodry="2000.0" uh="0.065" a="0.14" nn="1.3" permeabilitytype="1" c1="0.0015" alpha0="0.1" hc="0.75" n="10.0"/>
      <!-- BSB capacity + piecewise linear permeability -->
      <nlisomoisturemat d="2400.0" isothermtype="5" rhodry="2000.0" vm="0.01" c="20.0" k="0.85" permeabilitytype="1" c1="0.0015" alpha0="0.1" hc="0.75" n="10.0"/>
      <!-- BSB capacity + Xi permeability -->
      <nlisomoisturemat d="2400.0" isothermtype="5" rhodry="2000.0" vm="0.01" c="20.0" k="0.85" permeabilitytype="2" alphah="0.0005" betah="0.001" gammah="3.8"/>
    </Materials>
    <BoundaryConditions>
      <BoundaryCondition loadtimefunction="1" dofs="14" values="1.0" set="2"/>
    </BoundaryConditions>
    <InitialConditions>
      <InitialCondition conditions="u 0.99" dofs="14" set="1"/>
    </InitialConditions>
    <LoadTimeFunctions>
      <ConstantFunction f_t_="0.5"/>
    </LoadTimeFunctions>
    <Sets>
      <Set noderanges="1-42"/>
      <Set nodes="3 6 9 12 15 18 21 24 27 30 33 36 39 42"/>
    </Sets>
  </Domain>
  <ExportModules>
    <errorcheck tolerance="1e-05">
      <NODE tStep="5" number="1" dof="14" unknown="d" value="0.715801903"/>
      <NODE tStep="5" number="7" dof="14" unknown="d" value="0.762862593"/>
      <NODE tStep="5" number="13" dof="14" unknown="d" value="0.907642137"/>
      <NODE tStep="5" number="19" dof="14" unknown="d" value="0.793992624"/>
      <NODE tStep="5" number="25" dof="14" unknown="d" value="0.777698624"/>
      <NODE tStep="5" number="31" dof="14" unknown="d" value="0.78234491"/>
      <NODE tStep="5" number="37" dof="14" unknown="d" value="0.846765183"/>
    </errorcheck>
  </ExportModules>
</oofem>
